[{
	"id": 1,
	"location": "30%, 300px",
	"img": "http://lorempixel.com/30/30/people",
	"floor": 1,
	"title": "Ты просто Шерлок! Ты прошел первый купон!",
	"description": "Можешь оформить скидку <b>2%</b> на жалюзи прямо сейчас. Для этого оставь свой email и мы отправим на него промо-код с инструкцией."
}, {
	"id": 2,
	"location": "30%, 300px",
	"img": "http://lorempixel.com/30/30/people",
	"floor": 1,
	"title": "Ура, второй купон!",
	"description": "Можешь оформить скидку <b>4%</b> на жалюзи прямо сейчас. Для этого оставь свой email и мы отправим на него промо-код с инструкцией."
}]
